README.md
setup.py
amphora/__init__.py
amphora/amphora.py
amphora/amphora_access.py
amphora/amphora_file.py
amphora/amphora_signal_pusher.py
amphora/amphora_signals.py
amphora/base.py
amphora/client.py
amphora/errors.py
amphora/utilities.py
amphora_api_client/__init__.py
amphora_api_client/api_client.py
amphora_api_client/configuration.py
amphora_api_client/exceptions.py
amphora_api_client/rest.py
amphora_api_client/api/__init__.py
amphora_api_client/api/account_api.py
amphora_api_client/api/activities_api.py
amphora_api_client/api/amphorae_api.py
amphora_api_client/api/applications_api.py
amphora_api_client/api/authentication_api.py
amphora_api_client/api/feeds_api.py
amphora_api_client/api/geo_api.py
amphora_api_client/api/identity_api.py
amphora_api_client/api/invitations_api.py
amphora_api_client/api/organisations_api.py
amphora_api_client/api/permission_api.py
amphora_api_client/api/search_api.py
amphora_api_client/api/terms_of_use_api.py
amphora_api_client/api/time_series_api.py
amphora_api_client/api/users_api.py
amphora_api_client/api/version_api.py
amphora_api_client/models/__init__.py
amphora_api_client/models/access_level_query.py
amphora_api_client/models/access_level_response.py
amphora_api_client/models/account_information.py
amphora_api_client/models/activity.py
amphora_api_client/models/address.py
amphora_api_client/models/aggregate_series.py
amphora_api_client/models/aggregate_variable.py
amphora_api_client/models/all_access_rule.py
amphora_api_client/models/amphora_reference.py
amphora_api_client/models/amphora_user.py
amphora_api_client/models/app_location.py
amphora_api_client/models/application.py
amphora_api_client/models/basic_amphora.py
amphora_api_client/models/categorical_variable.py
amphora_api_client/models/collection_response_of_application.py
amphora_api_client/models/collection_response_of_feed_item.py
amphora_api_client/models/collection_response_of_invitation.py
amphora_api_client/models/collection_response_of_invoice.py
amphoradata.egg-info/PKG-INFO
amphoradata.egg-info/SOURCES.txt
amphoradata.egg-info/dependency_links.txt
amphoradata.egg-info/requires.txt
amphoradata.egg-info/top_level.txt
