Metadata-Version: 1.0
Name: amphoradata
Version: 0.10.29
Summary: Amphora Data
Home-page: UNKNOWN
Author: OpenAPI Generator community
Author-email: team@openapitools.org
License: UNKNOWN
Keywords: OpenAPI,OpenAPI-Generator,Amphora Data
Platform: UNKNOWN
